meegnet/__init__.py
meegnet/algorithms.py
meegnet/dataloaders.py
meegnet/layer.py
meegnet/misc.py
meegnet/ml_parser.py
meegnet/network.py
meegnet/params.py
meegnet/parsing.py
meegnet/utils.py
meegnet/viz.py
meegnet-0.2.5.dist-info/LICENSE.txt
meegnet-0.2.5.dist-info/METADATA
meegnet-0.2.5.dist-info/WHEEL
meegnet-0.2.5.dist-info/top_level.txt
meegnet-0.2.5.dist-info/RECORD
