Metadata-Version: 2.1
Name: meegnet
Version: 0.2.5
Summary: A set of MEG-optimized ANNs and visualization tools.
Author: Arthur Dehgan
License: MIT
License-File: LICENSE.txt
Requires-Dist: mne
Requires-Dist: torch
Requires-Dist: numpy
Requires-Dist: scipy
Requires-Dist: pandas
Requires-Dist: scikit-learn
Requires-Dist: configargparse
Requires-Dist: torchvision
Requires-Dist: huggingface-hub
Requires-Dist: grad-cam
